theto/__init__.py
theto/bokeh_utils.py
theto/color_utils.py
theto/coordinate_utils.py
theto/gmaps_utils.py
theto/theto.py
theto-0.2.1.dist-info/LICENSE
theto-0.2.1.dist-info/METADATA
theto-0.2.1.dist-info/WHEEL
theto-0.2.1.dist-info/top_level.txt
theto-0.2.1.dist-info/RECORD
