Metadata-Version: 2.1
Name: theto
Version: 0.2.1
Summary: Workflow automation for exploring location data
Home-page: https://github.com/Valassis-Digital-Media/theto
Author: Valassis Digital
License: BSD 3-Clause
Platform: Linux
Platform: Mac OSX
Platform: Windows
Requires-Dist: bokeh (>=1.0)
Requires-Dist: pandas
Requires-Dist: numpy
Requires-Dist: shapely
Requires-Dist: pyproj
